download_dandi_sample.py
spikesort.py
speed_spike_sort-0.1.0.dist-info/licenses/LICENSE
speed_spike_sort-0.1.0.dist-info/METADATA
speed_spike_sort-0.1.0.dist-info/WHEEL
speed_spike_sort-0.1.0.dist-info/entry_points.txt
speed_spike_sort-0.1.0.dist-info/top_level.txt
speed_spike_sort-0.1.0.dist-info/RECORD
