Metadata-Version: 2.4
Name: speed-spike-sort
Version: 0.1.0
Summary: High-performance framework for neural spike sorting of electrophysiological data
Author: NileshArnaiya
License-Expression: CC0-1.0
Project-URL: Homepage, https://github.com/NileshArnaiya/Speed-Spike-Sort
Requires-Python: >=3.6
License-File: LICENSE
Dynamic: license-file
